{
  "id": "9.3",
  "name": "Tournoi",
  "world": 9,
  "startCoins": 350,
  "allowedTiles": [
    "coin",
    "lava",
    "water",
    "fan",
    "magnet",
    "catapult"
  ],
  "loseEscaped": 2,
  "waves": [
    {
      "delayMs": 12000,
      "visitors": [
        {
          "type": "stiltman",
          "lane": 2,
          "delayMs": 0
        },
        {
          "type": "basic",
          "lane": 1,
          "delayMs": 2500
        },
        {
          "type": "basic",
          "lane": 3,
          "delayMs": 4000
        },
        {
          "type": "tank",
          "lane": 0,
          "delayMs": 6500
        },
        {
          "type": "stiltman",
          "lane": 1,
          "delayMs": 9500
        },
        {
          "type": "basic",
          "lane": 1,
          "delayMs": 12500
        },
        {
          "type": "basic",
          "lane": 4,
          "delayMs": 12500
        },
        {
          "type": "stiltman",
          "lane": 1,
          "delayMs": 15500
        },
        {
          "type": "basic",
          "lane": 1,
          "delayMs": 18500
        },
        {
          "type": "basic",
          "lane": 4,
          "delayMs": 18500
        }
      ]
    },
    {
      "delayMs": 30000,
      "visitors": [
        {
          "type": "stiltman",
          "lane": 0,
          "delayMs": 0
        },
        {
          "type": "stiltman",
          "lane": 4,
          "delayMs": 1500
        },
        {
          "type": "tank",
          "lane": 2,
          "delayMs": 3000
        },
        {
          "type": "vip",
          "lane": 1,
          "delayMs": 5000
        },
        {
          "type": "basic",
          "lane": 3,
          "delayMs": 6500
        },
        {
          "type": "stiltman",
          "lane": 4,
          "delayMs": 10250
        },
        {
          "type": "stiltman",
          "lane": 4,
          "delayMs": 14000
        },
        {
          "type": "stiltman",
          "lane": 4,
          "delayMs": 17000
        },
        {
          "type": "stiltman",
          "lane": 4,
          "delayMs": 20000
        },
        {
          "type": "tank",
          "lane": 3,
          "delayMs": 20000
        }
      ]
    },
    {
      "delayMs": 56000,
      "visitors": [
        {
          "type": "stiltman",
          "lane": 1,
          "delayMs": 0
        },
        {
          "type": "stiltman",
          "lane": 3,
          "delayMs": 800
        },
        {
          "type": "tank",
          "lane": 0,
          "delayMs": 2500
        },
        {
          "type": "tank",
          "lane": 4,
          "delayMs": 3500
        },
        {
          "type": "vip",
          "lane": 2,
          "delayMs": 5000
        },
        {
          "type": "basic",
          "lane": 1,
          "delayMs": 7000
        },
        {
          "type": "basic",
          "lane": 3,
          "delayMs": 7800
        },
        {
          "type": "stiltman",
          "lane": 0,
          "delayMs": 10800
        },
        {
          "type": "stiltman",
          "lane": 3,
          "delayMs": 13800
        },
        {
          "type": "tank",
          "lane": 1,
          "delayMs": 13800
        },
        {
          "type": "stiltman",
          "lane": 0,
          "delayMs": 16800
        },
        {
          "type": "stiltman",
          "lane": 3,
          "delayMs": 19800
        },
        {
          "type": "tank",
          "lane": 1,
          "delayMs": 19800
        }
      ]
    }
  ],
  "stars": {
    "1": {
      "escapedMax": 1
    },
    "2": {
      "escapedMax": 1
    },
    "3": {
      "escapedMax": 0
    }
  }
}
